LICENSE.txt
README.md
setup.cfg
setup.py
blinpy/__init__.py
blinpy/models.py
blinpy/utils.py
blinpy.egg-info/PKG-INFO
blinpy.egg-info/SOURCES.txt
blinpy.egg-info/dependency_links.txt
blinpy.egg-info/requires.txt
blinpy.egg-info/top_level.txt