Metadata-Version: 2.1
Name: blinpy
Version: 0.1.12
Summary: Bayesian Linear Models in Python
Home-page: https://github.com/solbes/blinpy
Download-URL: https://github.com/solbes/blinpy/archive/refs/tags/0.1.12.tar.gz
Author: Antti Solonen
Author-email: antti.solonen@gmail.com
License: MIT
Keywords: bayes,linear,gam
Classifier: Development Status :: 3 - Alpha
Classifier: Intended Audience :: Science/Research
Classifier: Topic :: Scientific/Engineering :: Artificial Intelligence
Classifier: License :: OSI Approved :: MIT License
Classifier: Programming Language :: Python :: 3
License-File: LICENSE.txt
Requires-Dist: numpy
Requires-Dist: pandas
Requires-Dist: jsonpickle
Requires-Dist: scipy
Provides-Extra: dev
Requires-Dist: pytest; extra == "dev"
Provides-Extra: quadprog
Requires-Dist: quadprog; extra == "quadprog"
Provides-Extra: cvxpy
Requires-Dist: cvxpy; extra == "cvxpy"
